djapy/__init__.py
djapy/core/__init__.py
djapy/core/d_types.py
djapy/core/defaults.py
djapy/core/labels.py
djapy/core/mid.py
djapy/core/parser.py
djapy/core/response.py
djapy/core/type_check.py
djapy/core/typing_utils.py
djapy/core/view_func.py
djapy/core/auth/__init__.py
djapy/core/auth/auth.py
djapy/core/auth/dec.py
djapy/core/dec/__init__.py
djapy/core/dec/async_dec.py
djapy/core/dec/base_dec.py
djapy/core/dec/sync_dec.py
djapy/openapi/__init__.py
djapy/openapi/defaults.py
djapy/openapi/icons.py
djapy/openapi/info.py
djapy/openapi/openapi_path.py
djapy/pagination/__init__.py
djapy/pagination/base_pagination.py
djapy/pagination/cursor_pagination.py
djapy/pagination/dec.py
djapy/pagination/offset_pagination.py
djapy/pagination/page_number_pagination.py
djapy/schema/__init__.py
djapy/schema/handle.py
djapy/schema/schema.py
djapy/schema/user.py
djapy/templates/djapy/swagger_cdn.html
djapy-0.2.1.dist-info/METADATA
djapy-0.2.1.dist-info/WHEEL
djapy-0.2.1.dist-info/top_level.txt
djapy-0.2.1.dist-info/RECORD
