Metadata-Version: 2.2
Name: djapy
Version: 0.2.1
Summary: Fast, zero-boilerplate Django REST API framework with pure Python typing!
Home-page: https://github.com/Bishwas-py/djapy
Project-URL: Documentation, https://djapy.io
Classifier: Programming Language :: Python :: 3
Classifier: Programming Language :: Python :: 3.10
Classifier: Programming Language :: Python :: 3.11
Classifier: Programming Language :: Python :: 3.12
Classifier: Programming Language :: Python :: 3.13
Classifier: License :: OSI Approved :: GNU General Public License v3 (GPLv3)
Classifier: Operating System :: OS Independent
Requires-Python: >=3.10
Requires-Dist: Django
Requires-Dist: pydantic
Dynamic: classifier
Dynamic: description
Dynamic: description-content-type
Dynamic: home-page
Dynamic: project-url
Dynamic: requires-dist
Dynamic: requires-python
Dynamic: summary
